picosnitch.py
picosnitch-1.0.3.dist-info/LICENSE
picosnitch-1.0.3.dist-info/METADATA
picosnitch-1.0.3.dist-info/WHEEL
picosnitch-1.0.3.dist-info/entry_points.txt
picosnitch-1.0.3.dist-info/top_level.txt
picosnitch-1.0.3.dist-info/RECORD
