Metadata-Version: 2.1
Name: picosnitch
Version: 1.0.3
Summary: Monitor network traffic per executable using BPF
Home-page: https://elesiuta.github.io/picosnitch
License: GPLv3
Classifier: Operating System :: POSIX :: Linux
Classifier: Programming Language :: Python :: 3
Classifier: License :: OSI Approved :: GNU General Public License v3 or later (GPLv3+)
Classifier: Topic :: System :: Networking :: Monitoring
Classifier: Topic :: System :: Monitoring
Classifier: Topic :: Security
Requires-Python: >=3.8
License-File: LICENSE
Requires-Dist: psutil
Provides-Extra: enable_dash
Requires-Dist: dash ; extra == 'enable_dash'
Requires-Dist: pandas ; extra == 'enable_dash'
Requires-Dist: plotly ; extra == 'enable_dash'
Provides-Extra: enable_geoip
Requires-Dist: geoip2 ; extra == 'enable_geoip'
Provides-Extra: enable_notifications
Requires-Dist: dbus-python ; extra == 'enable_notifications'
Provides-Extra: enable_sql
Requires-Dist: psycopg ; extra == 'enable_sql'
Requires-Dist: pymysql ; extra == 'enable_sql'
Provides-Extra: enable_themes
Requires-Dist: dash-bootstrap-components ; extra == 'enable_themes'
Requires-Dist: dash-bootstrap-templates ; extra == 'enable_themes'
Provides-Extra: enable_virustotal
Requires-Dist: requests ; extra == 'enable_virustotal'
Provides-Extra: full
Requires-Dist: dash ; extra == 'full'
Requires-Dist: pandas ; extra == 'full'
Requires-Dist: plotly ; extra == 'full'
Requires-Dist: geoip2 ; extra == 'full'
Requires-Dist: psycopg ; extra == 'full'
Requires-Dist: pymysql ; extra == 'full'
Requires-Dist: dash-bootstrap-components ; extra == 'full'
Requires-Dist: dash-bootstrap-templates ; extra == 'full'
Requires-Dist: requests ; extra == 'full'
